tagbit/__init__.py
tagbit/handlers.py
tagbit/reader.py
tagbit/status.py
tagbit/utils.py
TagBit-1.0.dist-info/LICENSE
TagBit-1.0.dist-info/METADATA
TagBit-1.0.dist-info/WHEEL
TagBit-1.0.dist-info/top_level.txt
TagBit-1.0.dist-info/RECORD
