Metadata-Version: 2.2
Name: TagBit
Version: 1.0
Summary: A lightweight python library for reading and writing to NFC tags via PC/SC
Home-page: https://github.com/ModestBitboard/TagBit
Author: Akito Hoshi
License: MIT
Classifier: Programming Language :: Python :: 3
Classifier: License :: OSI Approved :: MIT License
Classifier: Operating System :: Microsoft :: Windows
Classifier: Operating System :: MacOS :: MacOS X
Classifier: Operating System :: Unix
License-File: LICENSE
Requires-Dist: pyscard~=2.2.0
Requires-Dist: ndeflib~=0.3.3
Dynamic: author
Dynamic: classifier
Dynamic: description
Dynamic: description-content-type
Dynamic: home-page
Dynamic: license
Dynamic: requires-dist
Dynamic: summary
